jetblack_open_meteo/__init__.py
jetblack_open_meteo/air_quality.py
jetblack_open_meteo/climate_change.py
jetblack_open_meteo/elevation.py
jetblack_open_meteo/ensemble_models.py
jetblack_open_meteo/flood.py
jetblack_open_meteo/geocoding.py
jetblack_open_meteo/historical_weather.py
jetblack_open_meteo/marine_forecast.py
jetblack_open_meteo/py.typed
jetblack_open_meteo/types.py
jetblack_open_meteo/utils.py
jetblack_open_meteo/weather_forecast/__init__.py
jetblack_open_meteo/weather_forecast/dwd_icon.py
jetblack_open_meteo/weather_forecast/ecmwf.py
jetblack_open_meteo/weather_forecast/gfs.py
jetblack_open_meteo/weather_forecast/weather_forecast.py
jetblack_open_meteo-1.0.0a0.dist-info/METADATA
jetblack_open_meteo-1.0.0a0.dist-info/WHEEL
jetblack_open_meteo-1.0.0a0.dist-info/top_level.txt
jetblack_open_meteo-1.0.0a0.dist-info/RECORD
