Metadata-Version: 2.1
Name: jetblack-open-meteo
Version: 1.0.0a0
Summary: Client implementation for open-meteo
Author-email: Rob Blackbourn <rob.blackbourn@gmail.com>
Project-URL: Homepage, https://github.com/rob-blackbourn/jetblack-open-meteo
Project-URL: Issues, https://github.com/rob-blackbourn/jetblack-open-meteo/issues
Classifier: Programming Language :: Python :: 3
Classifier: License :: OSI Approved :: MIT License
Classifier: Operating System :: OS Independent
Requires-Python: >=3.8
